[
  {
    "category": "UI",
    "guid": "95655672-2342-4321-8291-321312312312",
    "name": "NotifySync",
    "description": "NotifySync transforme l'interface de Jellyfin en ajoutant une icône de notification (cloche) native. Il permet à vos utilisateurs de voir instantanément les derniers ajouts (Films, Séries, Musique) sans quitter leur page actuelle, le tout avec un design fluide inspiré des plateformes de streaming majeures.",
    "owner": "Peterdu1109 & ElieM",
    "overview": "Ajoute un centre de notifications (cloche) pour voir les nouveaux médias sans quitter la page.",
    "supportUrl": "https://github.com/",
    "versions": [
      {
        "version": "4.6.6.0",
        "changelog": "Release Notes: https://github.com/peterdu1109/NotifySync",
        "targetAbi": "10.11.0.0",
        "sourceUrl": "https://github.com/peterdu1109/NotifySync/releases/download/v4.6.6/NotifySync.zip",
        "checksum": "3AD65EF6768E43EBA09A08438DE21E3A",
        "timestamp": "2026-01-17T19:30:00Z"
      }
    ]
  }
]
